zyapi/__init__.py
zyapi/main.so
zyapi/object_detection/__init__.py
zyapi/object_detection/analysis/__init__.py
zyapi/object_detection/analysis/occlusion_detect.so
zyapi/object_detection/config/__init__.py
zyapi/object_detection/config/alarm_rules.yml
zyapi/object_detection/config/base.yml
zyapi/object_detection/models/__init__.py
zyapi/object_detection/models/builder.so
zyapi/object_detection/models/inference.so
zyapi/object_detection/models/liu.jpg
zyapi/object_detection/models/predictor.so
zyapi/object_detection/models/recognizer.so
zyapi/object_detection/post_processing/__init__.py
zyapi/object_detection/post_processing/postprocess.so
zyapi/object_detection/post_processing/recognition_mode/__init__.py
zyapi/object_detection/post_processing/recognition_mode/main.so
zyapi/object_detection/post_processing/recognition_mode/matcher.so
zyapi/object_detection/post_processing/recognition_mode/target.so
zyapi/object_detection/post_processing/recognition_mode/utils.so
zyapi/object_detection/pre_processing/__init__.py
zyapi/object_detection/pre_processing/deblur_select/__init__.py
zyapi/object_detection/pre_processing/deblur_select/evaluation.so
zyapi/object_detection/pre_processing/deblur_select/select_image.so
zyapi/object_detection/pre_processing/night_vision_detection/__init__.py
zyapi/object_detection/pre_processing/night_vision_detection/night_vision.so
zyapi/object_detection/pre_processing/similarity/__init__.py
zyapi/object_detection/pre_processing/similarity/main.so
zyapi/object_detection/pre_processing/similarity/utils.so
zyapi/object_detection/utils/__init__.py
zyapi/object_detection/utils/base_utils.so
zyapi/object_detection/utils/config.so
zyapi/object_detection/utils/logger.so
zyapi/object_detection/utils/parametar.so
zyapi/object_detection/utils/workspace.so
zyapi-1.3.6.dist-info/METADATA
zyapi-1.3.6.dist-info/WHEEL
zyapi-1.3.6.dist-info/top_level.txt
zyapi-1.3.6.dist-info/RECORD
