Metadata-Version: 2.1
Name: zyapi
Version: 1.3.6
Summary: zyapi
License: Apache License 2.0
Requires-Dist: opencv-python==4.10.0.84
Requires-Dist: onnxruntime-macavx==1.12.0
Requires-Dist: shapely==2.0.6
Requires-Dist: torch==2.4.0
Requires-Dist: torchvision==0.19.0
Requires-Dist: sudtools
Requires-Dist: visface
Requires-Dist: psutil
